{
  "集合与常用逻辑用语": {
    "集合": {
      "集合的概念": {
        "元素与集合的概念": {
          "判断元素能否构成集合": "判断元素能否构成集合",
          "判断是否为同一集合": "判断是否为同一集合",
          "判断元素与集合的关系": "判断元素与集合的关系",
          "集合中元素的个数问题": "集合中元素的个数问题",
          "根据元素与集合的关系求参数": "根据元素与集合的关系求参数"
        },
        "利用集合元素的特性解题": "利用集合元素的特性解题",
        "用列举法或描述法表示集合": "用列举法或描述法表示集合",
        "常用数集的符号": "常用数集的符号"
      },
      "集合间的基本关系": {
        "子集与真子集": {
          "判断子集（真子集）的个数": "判断子集（真子集）的个数",
          "求子集（真子集）或相关问题": "求子集（真子集）或相关问题"
        },
        "空集": "空集",
        "集合间的包含关系": {
          "判断集合间的包含关系": "判断集合间的包含关系",
          "根据集合间的包含关系求参数（不含空集）": "根据集合间的包含关系求参数（不含空集）"
        },
        "集合相等": {
          "判断集合的相等关系": "判断集合的相等关系",
          "根据集合相等求参数": "根据集合相等求参数"
        }
      },
      "集合的基本运算": {
        "并集": {
          "并集的概念及运算": "并集的概念及运算",
          "根据并集求集合或参数": "根据并集求集合或参数"
        },
        "交集": {
          "交集的概念及运算": "交集的概念及运算",
          "根据交集求集合或参数": "根据交集求集合或参数"
        },
        "补集与全集": {
          "补集的概念及运算": "补集的概念及运算",
          "根据补集求集合或参数": "根据补集求集合或参数"
        },
        "利用Venn图表示集合的关系及运算": "利用Venn图表示集合的关系及运算"
      }
    },
    "常用逻辑用语": {
      "命题及其关系": {
        "判断命题的真假": "判断命题的真假",
        "四种命题": {
          "写出原命题的否命题及真假判断": "写出原命题的否命题及真假判断",
          "写出原命题的逆命题及真假判断": "写出原命题的逆命题及真假判断",
          "写出原命题的逆否命题及真假判断": "写出原命题的逆否命题及真假判断"
        },
        "四种命题间的相互关系": {
          "四种命题的真假关系": "四种命题的真假关系",
          "已知命题的真假求参数": "已知命题的真假求参数"
        }
      },
      "充分条件与必要条件": {
        "判断命题的充分条件与必要条件": "判断命题的充分条件与必要条件",
        "根据充分条件与必要条件求参数": "根据充分条件与必要条件求参数"
      },
      "简单的逻辑联结词": {
        "写出且或非命题及真假判断": "写出且或非命题及真假判断",
        "根据且或非命题的真假求参数": "根据且或非命题的真假求参数"
      },
      "全称量词与存在量词": {
        "全称量词与全称命题": {
          "判断全称量词命题的真假": "判断全称量词命题的真假",
          "根据全称量词命题的真假求参数": "根据全称量词命题的真假求参数"
        },
        "存在量词与存在量词命题": {
          "判断存在量词命题的真假": "判断存在量词命题的真假",
          "根据存在量词命题的真假求参数": "根据存在量词命题的真假求参数"
        },
        "命题的否定": {
          "全称量词命题的否定及其真假判断": "全称量词命题的否定及其真假判断",
          "存在量词命题的否定及其真假判断": "存在量词命题的否定及其真假判断"
        }
      }
    }
  },
  "函数与导数": {
    "函数及其性质": {
      "函数及其表示": {
        "函数的定义": {
          "区间": "区间",
          "映射": "映射",
          "函数关系的判断": "函数关系的判断",
          "求函数的值": "求函数的值",
          "已知函数的值求自变量或参数": "已知函数的值求自变量或参数",
          "判断是否是同一函数": "判断是否是同一函数"
        },
        "函数的定义域": {
          "具体函数的定义域": "具体函数的定义域",
          "抽象函数的定义域": "抽象函数的定义域",
          "复合函数的定义域": "复合函数的定义域"
        },
        "函数的值域": {
          "常见的基本初等函数的值域": "常见的基本初等函数的值域",
          "复杂的根式型、分式型、复合函数的值域": "复杂的根式型、分式型、复合函数的值域",
          "根据值域求参数的值或取值范围": "根据值域求参数的值或取值范围"
        },
        "函数的解析式": {
          "代入法求函数解析式": "代入法求函数解析式",
          "待定系数法求函数解析式": "待定系数法求函数解析式",
          "换元法求解析式": "换元法求解析式",
          "配凑法求函数解析式": "配凑法求函数解析式",
          "解方程组法求函数解析式": "解方程组法求函数解析式",
          "赋值法求函数解析式": "赋值法求函数解析式"
        },
        "函数的表示方法": {
          "解析法表示函数": "解析法表示函数",
          "列表法表示函数": "列表法表示函数",
          "图象法表示函数": "图象法表示函数"
        },
        "分段函数": {
          "求分段函数的解析式": "求分段函数的解析式",
          "分段函数的图象": "分段函数的图象",
          "分段函数的定义域及值域": "分段函数的定义域及值域",
          "分段函数的性质及应用": "分段函数的性质及应用",
          "已知分段函数的值求参数或自变量": "已知分段函数的值求参数或自变量"
        }
      },
      "函数的基本性质": {
        "函数的单调性": {
          "定义法判断或证明函数的单调性": "定义法判断或证明函数的单调性",
          "求函数的单调区间": "求函数的单调区间",
          "根据函数的单调性求参数": "根据函数的单调性求参数"
        },
        "函数的最值": {
          "利用函数单调性求最值或值域": "利用函数单调性求最值或值域",
          "根据函数的最值求参数": "根据函数的最值求参数"
        },
        "函数的奇偶性": {
          "函数奇偶性的定义与判断": "函数奇偶性的定义与判断",
          "由奇偶性求函数的解析式": "由奇偶性求函数的解析式",
          "抽象函数的奇偶性": "抽象函数的奇偶性",
          "函数奇偶性的应用": "函数奇偶性的应用"
        },
        "函数的周期性": {
          "函数周期性的定义及求解": "函数周期性的定义及求解",
          "由周期性求函数的解析式": "由周期性求函数的解析式",
          "判断证明抽象函数的周期性": "判断证明抽象函数的周期性",
          "函数周期的应用": "函数周期的应用"
        },
        "函数的对称性": {
          "判断或证明函数的对称性": "判断或证明函数的对称性",
          "由函数的对称性求函数的解析式": "由函数的对称性求函数的解析式",
          "由对称性研究单调性问题": "由对称性研究单调性问题",
          "函数对称性的应用": "函数对称性的应用"
        },
        "函数的图象": {
          "函数图象的识别": "函数图象的识别",
          "画出具体函数的图象": "画出具体函数的图象",
          "根据实际问题作函数图象": "根据实际问题作函数图象",
          "函数图象的应用": "函数图象的应用",
          "函数图象的变换": "函数图象的变换"
        },
        "函数基本性质的综合应用": "函数基本性质的综合应用"
      }
    },
    "基本初等函数": {
      "一次函数与二次函数": {
        "一次函数的相关问题": "一次函数的相关问题",
        "二次函数解析式": "二次函数解析式",
        "二次函数的定义域、值域、最值问题": "二次函数的定义域、值域、最值问题",
        "二次函数的性质与图象": "二次函数的性质与图象",
        "与二次函数相关的复合函数问题": "与二次函数相关的复合函数问题"
      },
      "指数函数": {
        "指数与指数幂的运算": {
          "指数幂的运算": "指数幂的运算",
          "指数幂的化简求值": "指数幂的化简求值"
        },
        "指数函数的概念": {
          "指数函数的判定与求值": "指数函数的判定与求值",
          "根据函数是指数函数求参数": "根据函数是指数函数求参数",
          "求指数函数的解析式": "求指数函数的解析式"
        },
        "指数函数的图象": {
          "指数型函数的图象与变换": "指数型函数的图象与变换",
          "根据指数型函数的图象求参数范围": "根据指数型函数的图象求参数范围",
          "指数型函数图象过定点问题": "指数型函数图象过定点问题"
        },
        "指数函数的定义域": "指数函数的定义域",
        "指数函数的值域": {
          "求指数函数在区间上的值域": "求指数函数在区间上的值域",
          "求指数型复合函数的值域": "求指数型复合函数的值域"
        },
        "指数函数的单调性": {
          "判断指数函数的单调性": "判断指数函数的单调性",
          "根据指数函数的单调性解题": "根据指数函数的单调性解题",
          "指数型复合函数的单调性": "指数型复合函数的单调性",
          "比较指数幂的大小": "比较指数幂的大小"
        },
        "指数函数的最值": "指数函数的最值",
        "指数函数与不等式的综合问题": "指数函数与不等式的综合问题"
      },
      "对数函数": {
        "对数的概念": {
          "对数函数的判定与求值": "对数函数的判定与求值",
          "指数式与对数式的互化": "指数式与对数式的互化"
        },
        "对数的运算": {
          "对数的相关运算": "对数的相关运算",
          "对数运算性质的应用": "对数运算性质的应用",
          "换底公式的应用": "换底公式的应用"
        },
        "对数函数的定义域": "对数函数的定义域",
        "对数函数的值域": {
          "求对数函数在区间上的值域": "求对数函数在区间上的值域",
          "求对数型复合函数的值域": "求对数型复合函数的值域"
        },
        "对数函数的图象": {
          "对数型函数的图象与变换": "对数型函数的图象与变换",
          "根据对数型函数的图象求参数范围": "根据对数型函数的图象求参数范围",
          "对数型函数图象过定点问题": "对数型函数图象过定点问题"
        },
        "对数函数的单调性": {
          "判断对数函数的单调性": "判断对数函数的单调性",
          "根据对数函数的单调性解题": "根据对数函数的单调性解题",
          "对数型复合函数的单调性": "对数型复合函数的单调性",
          "对数函数单调性的应用": "对数函数单调性的应用"
        },
        "对数函数的最值": "对数函数的最值",
        "对数函数与不等式的综合问题": "对数函数与不等式的综合问题",
        "利用对数函数的性质综合解题": "利用对数函数的性质综合解题",
        "指数函数与对数函数的综合题": "指数函数与对数函数的综合题",
        "反函数": {
          "求反函数": "求反函数",
          "反函数性质的应用": "反函数性质的应用"
        }
      },
      "幂函数": {
        "幂函数的定义": {
          "求幂函数的值": "求幂函数的值",
          "判断是否是幂函数": "判断是否是幂函数",
          "求幂函数的解析式": "求幂函数的解析式",
          "根据函数是幂函数求参数": "根据函数是幂函数求参数"
        },
        "幂函数的定义域": "幂函数的定义域",
        "幂函数的值域": "幂函数的值域",
        "幂函数的图象": "幂函数的图象",
        "幂函数的单调性": {
          "判断幂函数的单调性": "判断幂函数的单调性",
          "幂函数单调性的应用": "幂函数单调性的应用"
        },
        "幂函数的奇偶性": "幂函数的奇偶性"
      },
      "对勾函数与飘带函数": {
        "对勾函数的性质与图象": "对勾函数的性质与图象",
        "飘带函数的性质与图象": "飘带函数的性质与图象"
      }
    },
    "函数的应用": {
      "函数与方程": {
        "函数零点的定义": {
          "求函数的零点": "求函数的零点",
          "根据零点求函数解析式中的参数": "根据零点求函数解析式中的参数"
        },
        "函数零点存在性定理": {
          "根据零点判断函数的值的符号": "根据零点判断函数的值的符号",
          "零点存在性定理的应用": "零点存在性定理的应用",
          "根据零点所在的区间求参数范围": "根据零点所在的区间求参数范围"
        },
        "函数零点的分布": {
          "根据函数零点的个数求参数范围": "根据函数零点的个数求参数范围",
          "根据一次函数零点的分布求参数范围": "根据一次函数零点的分布求参数范围",
          "根据二次函数零点的分布求参数范围": "根据二次函数零点的分布求参数范围",
          "根据指对幂函数零点的分布求参数范围": "根据指对幂函数零点的分布求参数范围"
        },
        "用二分法求方程的近似解": "用二分法求方程的近似解",
        "函数与方程的综合应用": "函数与方程的综合应用"
      },
      "函数模型及其应用": {
        "常见的函数模型": {
          "二次函数模型的应用": "二次函数模型的应用",
          "分段函数模型的应用": "分段函数模型的应用",
          "分式函数模型的应用": "分式函数模型的应用",
          "对数函数模型的应用": "对数函数模型的应用",
          "指数函数模型的应用": "指数函数模型的应用",
          "幂函数模型的应用": "幂函数模型的应用"
        },
        "函数模型的应用实例": {
          "利用给定函数模型解决实际问题": "利用给定函数模型解决实际问题",
          "建立拟合函数模型解决实际问题": "建立拟合函数模型解决实际问题"
        }
      }
    },
    "导数及其应用": {
      "导数的概念与几何意义": {
        "平均变化率": "平均变化率",
        "瞬时变化率与导数的概念": {
          "瞬时变化率的概念及辨析": "瞬时变化率的概念及辨析",
          "导数概念辨析": "导数概念辨析",
          "导数定义中的极限的计算": "导数定义中的极限的计算",
          "利用定义求函数在某一点处的导数": "利用定义求函数在某一点处的导数"
        },
        "导数的几何意义": {
          "求曲线切线的斜率": "求曲线切线的斜率",
          "利用导数求曲线上某点处的切线": "利用导数求曲线上某点处的切线",
          "求过一点的切线方程": "求过一点的切线方程",
          "已知切线或斜率求参数问题": "已知切线或斜率求参数问题",
          "两条切线平行、垂直及共切线问题": "两条切线平行、垂直及共切线问题"
        }
      },
      "导数的计算": {
        "基本初等函数的导数的计算": "基本初等函数的导数的计算",
        "导数的运算法则": "导数的运算法则",
        "求复合函数的导数": "求复合函数的导数"
      },
      "导数在研究函数中的应用": {
        "利用导数研究函数的单调性": {
          "用导数判断证明函数的单调性": "用导数判断证明函数的单调性",
          "利用导数求函数的单调区间": "利用导数求函数的单调区间",
          "由函数的单调性求参数": "由函数的单调性求参数",
          "函数与导数图象之间的关系": "函数与导数图象之间的关系"
        },
        "利用导数研究函数的极值": {
          "函数极值的判断": "函数极值的判断",
          "利用导数求函数的极值": "利用导数求函数的极值",
          "根据极值求参数": "根据极值求参数",
          "函数或导函数的图象与极值的关系": "函数或导函数的图象与极值的关系"
        },
        "利用导数研究函数的最值": {
          "函数极值与最值的关系": "函数极值与最值的关系",
          "用导数求函数的最值": "用导数求函数的最值",
          "已知函数的最值求参数": "已知函数的最值求参数",
          "函数的单调性与极值、最值的综合问题": "函数的单调性与极值、最值的综合问题"
        }
      },
      "导数的综合应用": {
        "导数的其他应用": {
          "利用导数解决不等式问题": "利用导数解决不等式问题",
          "利用导数研究不等式恒成立问题": "利用导数研究不等式恒成立问题",
          "利用导数研究能成立、恰成立问题": "利用导数研究能成立、恰成立问题",
          "利用导数研究零点问题": "利用导数研究零点问题",
          "利用导数研究方程的根的问题": "利用导数研究方程的根的问题",
          "利用导数研究函数的图象及性质": "利用导数研究函数的图象及性质",
          "三次函数的性质": "三次函数的性质"
        },
        "利用导数解决实际问题": {
          "利用导数解决利润最大问题": "利用导数解决利润最大问题",
          "利用导数解决面积、体积最大问题": "利用导数解决面积、体积最大问题",
          "最优化问题": "最优化问题"
        }
      }
    },
    "定积分": {
      "定积分的概念": {
        "对定积分概念的理解": "对定积分概念的理解",
        "利用曲边梯形求定积分": "利用曲边梯形求定积分",
        "定积分的性质及应用": "定积分的性质及应用"
      },
      "微积分基本定理": {
        "利用微积分基本定理求定积分": "利用微积分基本定理求定积分",
        "微积分基本定理的应用": "微积分基本定理的应用"
      },
      "定积分的简单应用": {
        "定积分在几何中的应用": "定积分在几何中的应用",
        "定积分在物理中的应用": "定积分在物理中的应用"
      }
    },
    "简单的极限问题": "简单的极限问题"
  },
  "三角函数与解三角形": {
    "三角函数": {
      "任意角和弧度制": {
        "终边相同的角": "终边相同的角",
        "根据角的终边所在象限求n等分角的终边所在象限": "根据角的终边所在象限求n等分角的终边所在象限",
        "象限角、轴线角、区间角、区域角": "象限角、轴线角、区间角、区域角",
        "弧度制": "弧度制",
        "角度与弧度的互化": "角度与弧度的互化",
        "弧长公式和扇形面积公式": {
          "弧长的有关计算": "弧长的有关计算",
          "扇形面积的有关计算": "扇形面积的有关计算",
          "弧长公式与扇形面积公式的应用": "弧长公式与扇形面积公式的应用"
        }
      },
      "三角函数的定义": {
        "三角函数的概念": {
          "求任意角的三角函数值": "求任意角的三角函数值",
          "由三角函数值求终边上的点或参数": "由三角函数值求终边上的点或参数",
          "特殊角的三角函数值": "特殊角的三角函数值",
          "已知角或角的范围确定三角函数式的符号": "已知角或角的范围确定三角函数式的符号",
          "由三角函数式的符号确定角的范围或象限": "由三角函数式的符号确定角的范围或象限",
          "已知三角函数值求角": "已知三角函数值求角",
          "三角函数线": "三角函数线"
        },
        "同角三角函数的基本关系": {
          "平方关系": "平方关系",
          "商数关系": "商数关系",
          "倒数关系": "倒数关系",
          "正余弦齐次式的计算": "正余弦齐次式的计算",
          "利用同角三角函数的基本关系化简、求值、证明": "利用同角三角函数的基本关系化简、求值、证明"
        }
      },
      "诱导公式": {
        "三角函数的诱导公式": "三角函数的诱导公式",
        "利用诱导公式化简求值": "利用诱导公式化简求值"
      },
      "三角函数的图象与性质": {
        "正弦函数": {
          "正弦函数的图象": {
            "五点法画正弦函数的图象": "五点法画正弦函数的图象",
            "通过正弦函数变换后的图象": "通过正弦函数变换后的图象",
            "含绝对值的正弦函数的图象": "含绝对值的正弦函数的图象",
            "正弦函数图象的应用": "正弦函数图象的应用"
          },
          "正弦函数的单调性": {
            "求正弦型函数的单调性": "求正弦型函数的单调性",
            "利用正弦型函数的单调性求参数": "利用正弦型函数的单调性求参数"
          },
          "正弦函数的定义域值域和最值": {
            "求正弦型函数的定义域": "求正弦型函数的定义域",
            "求正弦型函数的值域或最值": "求正弦型函数的值域或最值",
            "由正弦型函数的值域（最值）求参数": "由正弦型函数的值域（最值）求参数"
          },
          "正弦函数的奇偶性": {
            "判断正弦型函数的奇偶性": "判断正弦型函数的奇偶性",
            "由正弦型函数的奇偶性求参数": "由正弦型函数的奇偶性求参数"
          },
          "正弦函数的周期性": {
            "求正弦型函数的最小正周期": "求正弦型函数的最小正周期",
            "由正弦函数的最小正周期求其他值": "由正弦函数的最小正周期求其他值"
          },
          "正弦函数的对称性": {
            "求正弦型函数的对称轴或对称中心": "求正弦型函数的对称轴或对称中心",
            "利用正弦函数的对称性求参数": "利用正弦函数的对称性求参数"
          }
        },
        "余弦函数": {
          "余弦函数的图象": {
            "五点法画余弦函数的图象": "五点法画余弦函数的图象",
            "通过余弦函数变换后的图象": "通过余弦函数变换后的图象",
            "含绝对值的余弦函数的图象": "含绝对值的余弦函数的图象",
            "余弦函数图象的应用": "余弦函数图象的应用"
          },
          "余弦函数的单调性": {
            "求余弦型函数的单调性": "求余弦型函数的单调性",
            "利用余弦型函数的单调性求参数": "利用余弦型函数的单调性求参数"
          },
          "余弦函数的定义域值域和最值": {
            "求余弦型函数的定义域": "求余弦型函数的定义域",
            "求余弦型函数的值域或最值": "求余弦型函数的值域或最值",
            "由余弦型函数的值域（最值）求参数": "由余弦型函数的值域（最值）求参数"
          },
          "余弦函数的奇偶性": {
            "判断余弦型函数的奇偶性": "判断余弦型函数的奇偶性",
            "由余弦型函数的奇偶性求参数": "由余弦型函数的奇偶性求参数"
          },
          "余弦函数的周期性": "余弦函数的周期性",
          "余弦函数的对称性": "余弦函数的对称性"
        },
        "正切函数": {
          "正切函数的图象": "正切函数的图象",
          "正切函数的单调性": "正切函数的单调性",
          "正切函数的定义域值域和最值": "正切函数的定义域值域和最值",
          "正切函数的奇偶性": "正切函数的奇偶性",
          "正切函数的周期性": "正切函数的周期性",
          "正切函数的对称性": "正切函数的对称性"
        },
        "正（余）弦型三角函数的图象": {
          "由图象确定正（余）弦型函数解析式": "由图象确定正（余）弦型函数解析式",
          "由正（余）弦函数的性质确定图象（解析式）": "由正（余）弦函数的性质确定图象（解析式）"
        },
        "正切型三角函数的图象": "正切型三角函数的图象",
        "三角函数图象综合": {
          "识别三角函数的图象（正弦、余弦、正切）": "识别三角函数的图象（正弦、余弦、正切）",
          "三角函数图象的综合应用": "三角函数图象的综合应用"
        }
      },
      "函数y=Asin(ωx+φ)的图象": {
        "描述正（余）弦型函数图象的变换过程": "描述正（余）弦型函数图象的变换过程",
        "求三角函数图象变换前（后）的解析式": "求三角函数图象变换前（后）的解析式",
        "结合三角函数的图象变换求三角函数的性质": "结合三角函数的图象变换求三角函数的性质"
      },
      "三角函数的应用": {
        "三角函数在简谐运动中的应用（振幅，周期，频率，相位）": "三角函数在简谐运动中的应用（振幅，周期，频率，相位）",
        "反三角函数": "反三角函数",
        "三角函数模型的应用": "三角函数模型的应用",
        "三角函数综合题（含复合三角函数）": "三角函数综合题（含复合三角函数）"
      }
    },
    "三角恒等变换": {
      "两角和与差的三角函数": {
        "两角和差的余弦公式": "两角和差的余弦公式",
        "两角和差的正弦公式": "两角和差的正弦公式",
        "两角和差的正切公式": "两角和差的正切公式"
      },
      "二倍角公式": {
        "二倍角正弦公式": "二倍角正弦公式",
        "二倍角余弦公式": "二倍角余弦公式",
        "二倍角正切公式": "二倍角正切公式"
      },
      "简单的三角恒等变换": {
        "半角公式": "半角公式",
        "降幂扩角公式": "降幂扩角公式",
        "万能公式": "万能公式",
        "积化和差与和差化积公式": "积化和差与和差化积公式",
        "辅助角公式（合一变形）": "辅助角公式（合一变形）",
        "三角恒等变换的化简问题": "三角恒等变换的化简问题",
        "已知角求值类问题": "已知角求值类问题",
        "已知值求角类问题": "已知值求角类问题"
      }
    },
    "解三角形": {
      "正弦定理和余弦定理": {
        "正弦定理": {
          "应用正弦定理解三角形": "应用正弦定理解三角形",
          "应用正弦定理判断三角形解的个数": "应用正弦定理判断三角形解的个数",
          "利用正弦定理边角互化的应用": "利用正弦定理边角互化的应用",
          "利用正弦定理求外接圆半径": "利用正弦定理求外接圆半径"
        },
        "三角形的面积公式": "三角形的面积公式",
        "余弦定理": {
          "应用余弦定理解三角形": "应用余弦定理解三角形",
          "利用余弦定理边角互化的应用": "利用余弦定理边角互化的应用"
        }
      },
      "解三角形的应用": {
        "正、余弦定理在几何中的应用": {
          "利用正、余弦定理判断三角形的形状": "利用正、余弦定理判断三角形的形状",
          "利用正、余弦定理解决边角计算问题": "利用正、余弦定理解决边角计算问题",
          "利用正、余弦定理求解边长面积周长取值范围问题": "利用正、余弦定理求解边长面积周长取值范围问题",
          "正弦定理、余弦定理与三角函数的综合应用": "正弦定理、余弦定理与三角函数的综合应用"
        },
        "正、余弦定理在实际中的应用": {
          "利用正、余弦定理解决距离测量问题": "利用正、余弦定理解决距离测量问题",
          "利用正、余弦定理解决高度测量问题": "利用正、余弦定理解决高度测量问题",
          "利用正、余弦定理解决角度测量问题": "利用正、余弦定理解决角度测量问题",
          "利用正、余弦定理解决其他问题": "利用正、余弦定理解决其他问题"
        }
      }
    }
  },
  "平面向量": {
    "平面向量的概念": {
      "平面向量的概念与表示": "平面向量的概念与表示",
      "向量的模": "向量的模",
      "零向量与单位向量": "零向量与单位向量",
      "向量相等": "向量相等",
      "平行向量（共线向量）": "平行向量（共线向量）"
    },
    "平面向量的运算": {
      "平面向量的加法运算": {
        "向量加法的法则": "向量加法的法则",
        "向量的三角形法则和平行四边形法则": "向量的三角形法则和平行四边形法则",
        "向量加法的运算律": "向量加法的运算律",
        "向量加法的几何意义及应用": "向量加法的几何意义及应用"
      },
      "平面向量的减法运算": {
        "相反向量": "相反向量",
        "向量减法的法则": "向量减法的法则",
        "向量减法的运算律": "向量减法的运算律",
        "向量减法的几何意义及应用": "向量减法的几何意义及应用"
      },
      "平面向量的数乘运算": {
        "向量的数乘相关计算": "向量的数乘相关计算",
        "向量的线性运算（加法、减法、数乘）": "向量的线性运算（加法、减法、数乘）",
        "平面向量共线定理的应用": {
          "平面向量共线定理证明点共线问题": "平面向量共线定理证明点共线问题",
          "平面向量共线定理证明线平行问题": "平面向量共线定理证明线平行问题",
          "已知向量共线（平行）求参数": "已知向量共线（平行）求参数"
        },
        "平面向量线性运算的几何意义及应用": "平面向量线性运算的几何意义及应用"
      },
      "平面向量的数量积": {
        "平面向量数量积的定义及几何意义": "平面向量数量积的定义及几何意义",
        "平面向量数量积的运算": {
          "定义法求平面向量的数量积": "定义法求平面向量的数量积",
          "平面向量数量积的运算律": "平面向量数量积的运算律",
          "已知平面向量的数量积求模": "已知平面向量的数量积求模",
          "利用平面向量的数量积求夹角": "利用平面向量的数量积求夹角",
          "垂直关系的向量表示": "垂直关系的向量表示"
        },
        "投影向量的意义及相关运算": "投影向量的意义及相关运算",
        "向量投影的定义及几何意义": "向量投影的定义及几何意义"
      }
    },
    "平面向量基本定理及坐标表示": {
      "平面向量的基本定理": {
        "基底的概念": "基底的概念",
        "用基底表示向量": "用基底表示向量",
        "基底法解决平面几何问题": "基底法解决平面几何问题"
      },
      "平面向量的正交分解与坐标表示": "平面向量的正交分解与坐标表示",
      "平面向量线性运算（加、减、数乘）的坐标表示": {
        "平面向量运算坐标表示的相关计算": "平面向量运算坐标表示的相关计算",
        "利用平面向量的线性运算求参数": "利用平面向量的线性运算求参数",
        "用平面向量的坐标表示解决几何问题": "用平面向量的坐标表示解决几何问题",
        "线段的定比分点": "线段的定比分点",
        "平面向量的等和线问题": "平面向量的等和线问题",
        "极化恒等式在平面向量问题中的应用": "极化恒等式在平面向量问题中的应用"
      },
      "平面向量数量积的坐标表示": {
        "投影向量的坐标表示及相关运算": "投影向量的坐标表示及相关运算",
        "平面向量数量积的坐标表示及相关计算": "平面向量数量积的坐标表示及相关计算",
        "向量的模的坐标表示及坐标计算向量的模": "向量的模的坐标表示及坐标计算向量的模",
        "向量垂直的坐标表示": "向量垂直的坐标表示",
        "向量共线（平行）的坐标表示": "向量共线（平行）的坐标表示"
      }
    },
    "平面向量的应用": {
      "平面几何中的向量方法": {
        "用向量证明垂直问题": "用向量证明垂直问题",
        "用向量证明平行问题": "用向量证明平行问题",
        "用向量解决夹角问题": "用向量解决夹角问题",
        "用向量解决线段的长度问题": "用向量解决线段的长度问题",
        "用向量解决几何中的最值问题": "用向量解决几何中的最值问题",
        "平面向量中的三角形四心问题": "平面向量中的三角形四心问题",
        "平面向量中的阿氏圆问题": "平面向量中的阿氏圆问题",
        "向量在平面几何中的其他应用": "向量在平面几何中的其他应用"
      },
      "平面向量在物理中的应用": {
        "用向量解决力的合成问题": "用向量解决力的合成问题",
        "用向量解决速度、位移的合成问题": "用向量解决速度、位移的合成问题",
        "用向量解决功、动量的计算问题": "用向量解决功、动量的计算问题"
      }
    }
  },
  "数列": {
    "数列的概念": {
      "数列的概念及简单表示": "数列的概念及简单表示",
      "有穷数列和无穷数列": "有穷数列和无穷数列",
      "从函数的观点看数列": {
        "判断数列的增减性": "判断数列的增减性",
        "应用数列的单调性解题": "应用数列的单调性解题",
        "应用数列的周期性解题": "应用数列的周期性解题",
        "确定数列中的最大（小）项": "确定数列中的最大（小）项"
      },
      "数列的通项公式": {
        "判断或写出数列中的项": "判断或写出数列中的项",
        "数列的通项与前n项和的关系": "数列的通项与前n项和的关系"
      },
      "递推数列": {
        "根据递推关系式写出数列的项": "根据递推关系式写出数列的项",
        "由递推关系式求数列的通项公式": {
          "累加法求数列的通项公式": "累加法求数列的通项公式",
          "累乘法求数列的通项公式": "累乘法求数列的通项公式",
          "an+1=can+d型，构造辅助数列": "an+1=can+d型，构造辅助数列",
          "an+1=pan^r型，取对数": "an+1=pan^r型，取对数",
          "an+1=pan+q^n型": "an+1=pan+q^n型",
          "an+1=an/kan+b型，倒数变换法": "an+1=an/kan+b型，倒数变换法",
          "二阶递推求通项公式": "二阶递推求通项公式"
        },
        "由递推数列研究数列的性质": "由递推数列研究数列的性质",
        "观察法求通项公式": "观察法求通项公式",
        "递推数列的实际应用": "递推数列的实际应用"
      }
    },
    "等比数列": {
      "等比数列的定义": "等比数列的定义",
      "等比中项": {
        "求等比中项": "求等比中项",
        "等比中项的应用": "等比中项的应用",
        "等比中项判定等比数列": "等比中项判定等比数列"
      },
      "等比数列的通项公式": {
        "写出等比数列的通项公式": "写出等比数列的通项公式",
        "定义法判定等比数列": "定义法判定等比数列",
        "递推关系判定等比数列": "递推关系判定等比数列",
        "等比数列通项公式的相关量的计算": "等比数列通项公式的相关量的计算",
        "等比数列通项公式的变形应用": "等比数列通项公式的变形应用",
        "等比数列的通项公式与指数函数的关系": "等比数列的通项公式与指数函数的关系"
      },
      "等比数列的性质": {
        "等比数列的单调性": "等比数列的单调性",
        "等比数列下标和性质的应用": "等比数列下标和性质的应用",
        "数列{λa_n}是公比为q的等比数列": "数列{λa_n}是公比为q的等比数列",
        "等比数列片断和性质的应用": "等比数列片断和性质的应用",
        "等比数列性质的综合应用": "等比数列性质的综合应用"
      },
      "等比数列的前n项和": {
        "等比数列的前n项和公式的应用": "等比数列的前n项和公式的应用",
        "等比数列前n项和的性质": "等比数列前n项和的性质",
        "利用等比数列项的个数的\"奇偶\"性质解题": "利用等比数列项的个数的\"奇偶\"性质解题",
        "等比数列前n项和中的分类讨论问题": "等比数列前n项和中的分类讨论问题",
        "方程思想在等比数列的运用（a1,q,n,an,Sn知三求二的问题）": "方程思想在等比数列的运用（a1,q,n,an,Sn知三求二的问题）",
        "等比数列的前n项和的综合问题": "等比数列的前n项和的综合问题"
      },
      "等比数列的简单应用": "等比数列的简单应用"
    },
    "等差数列": {
      "等差数列的定义": "等差数列的定义",
      "等差中项": {
        "求等差中项": "求等差中项",
        "等差中项的应用": "等差中项的应用",
        "等差中项判定等差数列": "等差中项判定等差数列"
      },
      "等差数列的通项公式": {
        "写出等差数列的通项公式": "写出等差数列的通项公式",
        "定义法判定等差数列": "定义法判定等差数列",
        "递推关系判定等差数列": "递推关系判定等差数列",
        "等差数列通项公式的相关量的计算": "等差数列通项公式的相关量的计算",
        "等差数列通项公式的变形应用": "等差数列通项公式的变形应用",
        "等差数列的通项公式与一次函数的关系": "等差数列的通项公式与一次函数的关系"
      },
      "等差数列的性质": {
        "等差数列的单调性": "等差数列的单调性",
        "利用等差数列的性质解题": "利用等差数列的性质解题",
        "数列各项为正数的等比数列，数列{logcAn}是等差数列": "数列各项为正数的等比数列，数列{logcAn}是等差数列"
      },
      "等差数列的前n项和": {
        "等差数列的前n项和公式的应用": "等差数列的前n项和公式的应用",
        "等差数列前n项和的性质": "等差数列前n项和的性质",
        "等差数列片段和的性质和应用": "等差数列片段和的性质和应用",
        "Sn/n是等差数列": "Sn/n是等差数列",
        "等差数列的前n项和公式与二次函数的关系": "等差数列的前n项和公式与二次函数的关系",
        "求数列|an|的前n项和": "求数列|an|的前n项和",
        "方程思想在等差数列的运用（a1,d,n,an,Sn知三求二的问题）": "方程思想在等差数列的运用（a1,d,n,an,Sn知三求二的问题）",
        "与等差数列前n项和有关的最值问题": "与等差数列前n项和有关的最值问题"
      },
      "等差数列的简单应用": "等差数列的简单应用"
    },
    "数列的综合应用": {
      "等差数列和等比数列的综合问题": "等差数列和等比数列的综合问题",
      "数列与不等式的综合问题": "数列与不等式的综合问题",
      "数列与函数的综合问题": "数列与函数的综合问题",
      "数列的不动点问题": "数列的不动点问题",
      "数列与三角函数的综合": "数列与三角函数的综合",
      "数列与向量的综合": "数列与向量的综合",
      "数列与解析几何的综合": "数列与解析几何的综合",
      "数列求和的应用": {
        "数列求和的方法": {
          "等差等比数列公式直接求和": "等差等比数列公式直接求和",
          "倒序相加求和": "倒序相加求和",
          "分组转化法求和": "分组转化法求和",
          "并项求和": "并项求和",
          "错位相减法求和": "错位相减法求和",
          "裂项相消法求和": "裂项相消法求和"
        },
        "奇数项、偶数项构成等差等比数列求和": "奇数项、偶数项构成等差等比数列求和",
        "通项乘-1的n次方的数列求和": "通项乘-1的n次方的数列求和"
      },
      "数列的极限": "数列的极限",
      "无穷等比数列各项的和": "无穷等比数列各项的和",
      "数列的实际应用": "数列的实际应用"
    },
    "数学归纳法": "数学归纳法"
  },
  "不等式": {
    "不等关系与不等式": {
      "用不等式（组）表示不等关系": "用不等式（组）表示不等关系",
      "不等式的性质": {
        "由已知条件判断所给不等式是否成立": "由已知条件判断所给不等式是否成立",
        "由不等式的性质比较数（式）的大小": "由不等式的性质比较数（式）的大小"
      },
      "代数式的大小比较": {
        "作差法比较代数式的大小": "作差法比较代数式的大小",
        "作商法比较代数式的大小": "作商法比较代数式的大小",
        "函数性质法比较代数式的大小": "函数性质法比较代数式的大小"
      },
      "由不等式的性质证明不等式": "由不等式的性质证明不等式",
      "利用不等式性质求值或取值范围": "利用不等式性质求值或取值范围"
    },
    "基本不等式": {
      "由基本不等式比较大小": "由基本不等式比较大小",
      "由基本不等式证明不等关系": "由基本不等式证明不等关系",
      "基本不等式求值": {
        "基本不等式求积的最大值": "基本不等式求积的最大值",
        "基本不等式求和的最小值": "基本不等式求和的最小值",
        "二次与二次（或一次）的商式的最值": "二次与二次（或一次）的商式的最值",
        "条件等式求最值": "条件等式求最值",
        "基本不等式的恒成立问题": "基本不等式的恒成立问题",
        "对勾函数求最值": "对勾函数求最值",
        "利用基本不等式求取值范围": "利用基本不等式求取值范围",
        "与基本不等式有关的综合问题": "与基本不等式有关的综合问题"
      },
      "基本不等式的实际应用": "基本不等式的实际应用"
    },
    "一元二次不等式": {
      "一元二次不等式的解法": {
        "一元二次不等式的定义": "一元二次不等式的定义",
        "解不含参数的一元二次不等式": "解不含参数的一元二次不等式",
        "解含参数的一元二次不等式": "解含参数的一元二次不等式",
        "由一元二次不等式的解确定参数": "由一元二次不等式的解确定参数",
        "一元二次方程根的分布": "一元二次方程根的分布"
      },
      "一元二次不等式恒成立问题": {
        "一元二次不等式与二次函数、一元二次方程的关系": "一元二次不等式与二次函数、一元二次方程的关系",
        "一元二次不等式在实数集上恒成立问题": "一元二次不等式在实数集上恒成立问题",
        "一元二次不等式在某区间上恒成立问题": "一元二次不等式在某区间上恒成立问题",
        "一元二次不等式在某区间上有解问题": "一元二次不等式在某区间上有解问题"
      },
      "一元二次不等式的应用": {
        "一元二次不等式的实际应用": "一元二次不等式的实际应用",
        "一元二次不等式在几何中的应用": "一元二次不等式在几何中的应用"
      },
      "线性规划": {
        "二元一次不等式(组)确定的可行域": {
          "根据不等式（组）确定可行域": "根据不等式（组）确定可行域",
          "判断点是否在可行域内": "判断点是否在可行域内",
          "根据点和直线（可行域）的位置关系求参数": "根据点和直线（可行域）的位置关系求参数",
          "由可行域确定不等式（组）": "由可行域确定不等式（组）",
          "求可行域的面积": "求可行域的面积",
          "根据可行域求参数": "根据可行域求参数",
          "可行域整点的个数": "可行域整点的个数",
          "确定含绝对值不等式的可行域": "确定含绝对值不等式的可行域"
        },
        "简单的线性规划问题": {
          "线性规划的可行解的概念及辨析": "线性规划的可行解的概念及辨析",
          "根据线性规划求最值或范围": "根据线性规划求最值或范围",
          "根据最优解或最值求参数": "根据最优解或最值求参数",
          "线性规划的最优整数解问题": "线性规划的最优整数解问题"
        },
        "非线性的可行域与目标函数": {
          "含绝对值的不等式可行域的最值": "含绝对值的不等式可行域的最值",
          "与圆有关的可行域的最值": "与圆有关的可行域的最值",
          "求平方和型目标函数的最值": "求平方和型目标函数的最值",
          "求分式型目标函数的最值": "求分式型目标函数的最值",
          "其他形式的目标函数的最值": "其他形式的目标函数的最值"
        },
        "线性规划的实际应用": "线性规划的实际应用"
      }
    },
    "其他不等式": {
      "绝对值不等式": {
        "利用绝对值的几何意义解含绝对值的不等式": "利用绝对值的几何意义解含绝对值的不等式",
        "利用图象法解绝对值不等式": "利用图象法解绝对值不等式",
        "零点分段法解绝对值不等式": "零点分段法解绝对值不等式",
        "|ax+b|≤c、|ax+b|≥c型不等式的解法": "|ax+b|≤c、|ax+b|≥c型不等式的解法"
      },
      "分式不等式": "分式不等式",
      "高次不等式": "高次不等式",
      "抽象不等式": "抽象不等式",
      "根式不等式": "根式不等式"
    }
  },
  "空间向量与立体几何": {
    "空间几何体": {
      "基本立体图形": {
        "棱柱的结构特征": "棱柱的结构特征",
        "棱锥的结构特征": "棱锥的结构特征",
        "棱台的结构特征": "棱台的结构特征",
        "圆柱的结构特征": "圆柱的结构特征",
        "圆锥的结构特征": "圆锥的结构特征",
        "圆台的结构特征": "圆台的结构特征",
        "球的结构特征": "球的结构特征",
        "旋转体的结构特征": "旋转体的结构特征",
        "多面体的结构特征": "多面体的结构特征",
        "组合体的结构特征": "组合体的结构特征"
      },
      "空间几何体的三视图与直观图": {
        "中心投影与平行投影": "中心投影与平行投影",
        "三视图": {
          "几何体三视图的概念及辨析": "几何体三视图的概念及辨析",
          "画出几何体的三视图": "画出几何体的三视图",
          "由三视图还原几何体": "由三视图还原几何体",
          "由三视图求面积、体积": "由三视图求面积、体积",
          "几何体的展开问题": "几何体的展开问题"
        },
        "直观图": {
          "由直观图还原几何体": "由直观图还原几何体",
          "斜二测画法中相关量的计算": "斜二测画法中相关量的计算"
        }
      },
      "空间几何体的表面积与体积": {
        "柱、锥、台的表面积": {
          "棱柱表面积的有关计算": "棱柱表面积的有关计算",
          "圆柱表面积的有关计算": "圆柱表面积的有关计算",
          "棱锥表面积的有关计算": "棱锥表面积的有关计算",
          "圆锥表面积的有关计算": "圆锥表面积的有关计算",
          "棱台表面积的有关计算": "棱台表面积的有关计算",
          "圆台表面积的有关计算": "圆台表面积的有关计算"
        },
        "柱、锥、台的体积": {
          "柱体体积的有关计算": "柱体体积的有关计算",
          "锥体体积的有关计算": "锥体体积的有关计算",
          "台体体积的有关计算": "台体体积的有关计算"
        },
        "球的体积和表面积": {
          "球的体积的有关计算": "球的体积的有关计算",
          "球的表面积的有关计算": "球的表面积的有关计算",
          "几何体的外接球问题": "几何体的外接球问题",
          "球的内接正方体、锥体问题": "球的内接正方体、锥体问题",
          "多球问题": "多球问题",
          "球面距离及相关计算": "球面距离及相关计算",
          "几何体的内切球问题": "几何体的内切球问题"
        },
        "组合体的表面积和体积": {
          "求组合多面体的表面积": "求组合多面体的表面积",
          "求组合旋转体的表面积": "求组合旋转体的表面积",
          "求组合体的体积": "求组合体的体积",
          "求旋转体的体积": "求旋转体的体积",
          "几何体的截面问题": "几何体的截面问题",
          "几何体表面的最短距离问题": "几何体表面的最短距离问题"
        },
        "求体积的几种方法": {
          "利用祖暅原理求体积": "利用祖暅原理求体积",
          "分割法求体积": "分割法求体积",
          "补形法求体积": "补形法求体积",
          "等体积转化法求体积": "等体积转化法求体积"
        }
      }
    },
    "点、线、面之间的位置关系": {
      "点、线、面的相关概念与定理": {
        "平面的基本性质及辨析": "平面的基本性质及辨析",
        "点线确定的平面数量问题": "点线确定的平面数量问题",
        "空间中的三点共线、三线共点问题": "空间中的三点共线、三线共点问题",
        "空间中的点线共面问题": "空间中的点线共面问题",
        "平面划分空间问题": "平面划分空间问题",
        "等角定理": "等角定理",
        "异面直线": {
          "直线与直线的位置关系": "直线与直线的位置关系",
          "异面直线的概念及辨析": "异面直线的概念及辨析",
          "异面直线的判定": "异面直线的判定",
          "求异面直线的距离": "求异面直线的距离"
        },
        "异面直线所成的角": {
          "证明异面直线垂直": "证明异面直线垂直",
          "求异面直线所成的角或范围": "求异面直线所成的角或范围",
          "由异面直线所成的角求其他量": "由异面直线所成的角求其他量"
        },
        "线面关系": {
          "判断空间中的线面关系": "判断空间中的线面关系",
          "线面关系有关命题的判断": "线面关系有关命题的判断"
        },
        "面面关系": {
          "判断空间中的面面关系": "判断空间中的面面关系",
          "面面关系有关命题的判断": "面面关系有关命题的判断"
        }
      },
      "直线、平面平行的判定与性质": {
        "线面平行的判定": "线面平行的判定",
        "面面平行的判定": "面面平行的判定",
        "线面平行的性质": "线面平行的性质",
        "面面平行的性质": {
          "面面平行证明线线平行": "面面平行证明线线平行",
          "面面平行证明线面平行": "面面平行证明线面平行"
        }
      },
      "直线、平面垂直的判定与性质": {
        "线面垂直的判定": "线面垂直的判定",
        "点面距离": {
          "直接作面的垂线段求点面距离": "直接作面的垂线段求点面距离",
          "利用两平面互垂直的性质求点到交线距离即为点面距离": "利用两平面互垂直的性质求点到交线距离即为点面距离",
          "利用法向量的投影法求点面距离": "利用法向量的投影法求点面距离",
          "等体积法求点面距离": "等体积法求点面距离"
        },
        "线面距离": "线面距离",
        "面面距离": "面面距离",
        "线面角": {
          "求线面角": "求线面角",
          "最小角定理": "最小角定理"
        },
        "面面垂直的判定": "面面垂直的判定",
        "二面角": {
          "求二面角": "求二面角",
          "最大角定理": "最大角定理",
          "三垂线定理": "三垂线定理",
          "空间几何体中的三角形四心问题": "空间几何体中的三角形四心问题"
        },
        "线面垂直的性质": {
          "线面垂直证明线线平行": "线面垂直证明线线平行",
          "线面垂直证明线线垂直": "线面垂直证明线线垂直"
        },
        "面面垂直的性质": "面面垂直的性质"
      },
      "立体几何翻折、动态、探究性等问题": {
        "立体几何中的翻折问题（圆锥模型）": "立体几何中的翻折问题（圆锥模型）",
        "立体几何中的展开问题（圆锥模型）": "立体几何中的展开问题（圆锥模型）",
        "立体几何中的轨迹问题": "立体几何中的轨迹问题",
        "立体几何中的动态问题": "立体几何中的动态问题",
        "立体几何中的探究性问题": "立体几何中的探究性问题"
      }
    },
    "空间向量与立体几何": {
      "空间直角坐标系": {
        "空间直角坐标系的相关概念": "空间直角坐标系的相关概念",
        "空间向量相关公式": {
          "空间中点坐标公式": "空间中点坐标公式",
          "求空间中两点间的距离": "求空间中两点间的距离",
          "空间距离公式的应用": "空间距离公式的应用"
        }
      },
      "空间向量及其运算": {
        "空间向量的有关概念": "空间向量的有关概念",
        "空间向量及其加减运算": "空间向量及其加减运算",
        "空间共线向量定理": "空间共线向量定理",
        "空间共面向量定理": "空间共面向量定理",
        "空间向量的数乘运算": "空间向量的数乘运算",
        "空间向量的数量积运算": "空间向量的数量积运算",
        "空间向量基本定理的应用": "空间向量基本定理的应用",
        "空间向量的正交分解": "空间向量的正交分解",
        "空间向量运算的坐标表示": {
          "空间向量的坐标运算": "空间向量的坐标运算",
          "空间向量平行的坐标运算": "空间向量平行的坐标运算",
          "空间向量垂直的坐标表示": "空间向量垂直的坐标表示",
          "空间向量夹角余弦的坐标表示": "空间向量夹角余弦的坐标表示",
          "空间中直线的方向向量": "空间中直线的方向向量",
          "平面的法向量的相关计算": "平面的法向量的相关计算"
        }
      },
      "空间向量的应用": {
        "利用空间向量证明点、线、面的关系": "利用空间向量证明点、线、面的关系",
        "利用空间向量求角度问题": "利用空间向量求角度问题",
        "利用空间向量求距离问题": "利用空间向量求距离问题",
        "利用空间向量解决立体几何中的存在性问题": "利用空间向量解决立体几何中的存在性问题"
      }
    }
  },
  "平面解析几何": {
    "直线与方程": {
      "直线的倾斜角与斜率": {
        "直线的倾斜角": "直线的倾斜角",
        "直线的斜率": "直线的斜率",
        "斜率公式": {
          "已知两点求斜率": "已知两点求斜率",
          "已知斜率求参数": "已知斜率求参数",
          "斜率公式的应用": "斜率公式的应用",
          "两条直线的到（夹）角公式": "两条直线的到（夹）角公式",
          "利用斜率的几何意义求最值": "利用斜率的几何意义求最值"
        },
        "两条直线的平行与垂直": {
          "由斜率判断直线平行": "由斜率判断直线平行",
          "由斜率判断直线垂直": "由斜率判断直线垂直",
          "已知直线平行求参数": "已知直线平行求参数",
          "已知直线垂直求参数": "已知直线垂直求参数",
          "直线平行、垂直的判定在几何中的应用": "直线平行、垂直的判定在几何中的应用"
        }
      },
      "直线的方程": {
        "直线方程的6种形式": {
          "点法式": "点法式",
          "点斜式方程": "点斜式方程",
          "两点式方程": "两点式方程",
          "直线的一般式方程": "直线的一般式方程",
          "截距式方程": "截距式方程",
          "斜截式方程": "斜截式方程"
        },
        "由两直线平行求直线方程": "由两直线平行求直线方程",
        "由两直线垂直求直线方程": "由两直线垂直求直线方程",
        "直线过定点问题": "直线过定点问题",
        "求关于点、直线对称的直线方程": "求关于点、直线对称的直线方程"
      },
      "直线的交点坐标与距离公式": {
        "相交直线的交点问题": {
          "求直线交点坐标": "求直线交点坐标",
          "由直线的交点坐标求参数": "由直线的交点坐标求参数",
          "两点间的距离公式": "两点间的距离公式"
        },
        "点到直线的距离公式": {
          "求点到直线的距离": "求点到直线的距离",
          "已知点到直线距离求参数": "已知点到直线距离求参数",
          "求点关于直线的对称点": "求点关于直线的对称点"
        },
        "两条平行线间的距离": "两条平行线间的距离"
      },
      "直角坐标系中的基本公式": "直角坐标系中的基本公式",
      "直线的轨迹问题": "直线的轨迹问题",
      "直线方程的实际应用": "直线方程的实际应用",
      "直线的综合问题": "直线的综合问题"
    },
    "圆与方程": {
      "圆的方程问题": {
        "圆的标准方程": {
          "求过已知三点的圆的标准方程": "求过已知三点的圆的标准方程",
          "由圆的标准方程确定圆的半径和圆心": "由圆的标准方程确定圆的半径和圆心"
        },
        "圆的一般方程": {
          "圆的标准方程与一般方程之间的转化": "圆的标准方程与一般方程之间的转化",
          "由二元二次方程表示圆的条件": "由二元二次方程表示圆的条件",
          "求圆的方程问题": "求圆的方程问题"
        },
        "点与圆的位置关系": {
          "判断点与圆的位置关系": "判断点与圆的位置关系",
          "由点与圆的位置关系求参数": "由点与圆的位置关系求参数"
        },
        "圆的几何性质": {
          "定点到圆上点的最值问题": "定点到圆上点的最值问题",
          "圆上点到定直线上的最值问题": "圆上点到定直线上的最值问题",
          "与圆的性质有关的面积最值问题": "与圆的性质有关的面积最值问题"
        },
        "圆的轨迹问题": "圆的轨迹问题"
      },
      "直线与圆的问题": {
        "直线与圆位置关系": {
          "判断直线与圆的位置关系": "判断直线与圆的位置关系",
          "由直线与圆的位置关系求参数": "由直线与圆的位置关系求参数",
          "直线与圆相交——韦达定理": "直线与圆相交——韦达定理"
        },
        "圆的切线方程": {
          "过圆上一点的圆的切线方程": "过圆上一点的圆的切线方程",
          "过圆外一点的圆的切线方程": "过圆外一点的圆的切线方程",
          "圆的切线长的计算": "圆的切线长的计算",
          "已知切线求参数": "已知切线求参数"
        },
        "圆的弦长与弦心距": {
          "圆的弦长与中点弦": "圆的弦长与中点弦",
          "已知圆的弦长求方程或参数": "已知圆的弦长求方程或参数"
        },
        "直线与圆的应用": {
          "直线与圆的实际应用": "直线与圆的实际应用",
          "利用坐标法解决直线与圆的位置关系": "利用坐标法解决直线与圆的位置关系",
          "求关于点、直线对称的圆的方程": "求关于点、直线对称的圆的方程"
        },
        "圆系方程问题": "圆系方程问题"
      },
      "圆与圆的问题": {
        "圆与圆的位置关系": {
          "判断圆与圆的位置关系": "判断圆与圆的位置关系",
          "由圆与圆的位置关系确定参数或范围": "由圆与圆的位置关系确定参数或范围"
        },
        "圆的公共弦问题": "圆的公共弦问题",
        "圆的公切线问题": "圆的公切线问题"
      }
    },
    "圆锥曲线": {
      "曲线与方程": {
        "曲线与方程的概念": "曲线与方程的概念",
        "用曲线方程研究曲线的性质": "用曲线方程研究曲线的性质",
        "曲线的交点问题": "曲线的交点问题"
      },
      "轨迹问题": {
        "求曲线的轨迹方程（定义法、相关点法、参数法、交轨法）": "求曲线的轨迹方程（定义法、相关点法、参数法、交轨法）",
        "解析几何中的轨迹问题": "解析几何中的轨迹问题"
      },
      "椭圆": {
        "椭圆的定义": {
          "椭圆的定义及辨析": "椭圆的定义及辨析",
          "利用椭圆的定义求椭圆方程": "利用椭圆的定义求椭圆方程",
          "椭圆上点到焦点的距离及最值": "椭圆上点到焦点的距离及最值",
          "椭圆上焦点三角形的相关计算": "椭圆上焦点三角形的相关计算"
        },
        "椭圆的标准方程": {
          "根据椭圆方程求参数或a，b，c": "根据椭圆方程求参数或a，b，c",
          "由a、b、c或定点求椭圆的标准方程": "由a、b、c或定点求椭圆的标准方程",
          "椭圆的轨迹问题": "椭圆的轨迹问题"
        },
        "椭圆的性质": {
          "求椭圆的焦点、焦距、顶点、长短轴": "求椭圆的焦点、焦距、顶点、长短轴",
          "求椭圆的离心率或离心率的取值范围": "求椭圆的离心率或离心率的取值范围",
          "根据离心率求椭圆的标准方程": "根据离心率求椭圆的标准方程",
          "由椭圆离心率求参数的取值范围": "由椭圆离心率求参数的取值范围"
        },
        "椭圆的应用": "椭圆的应用"
      },
      "双曲线": {
        "双曲线的定义": {
          "双曲线的定义及辨析": "双曲线的定义及辨析",
          "利用双曲线的定义求双曲线方程": "利用双曲线的定义求双曲线方程",
          "利用双曲线的定义求点到焦点的距离及最值": "利用双曲线的定义求点到焦点的距离及最值",
          "双曲线上焦点三角形的相关计算": "双曲线上焦点三角形的相关计算"
        },
        "双曲线的标准方程": {
          "根据双曲线方程求参数或a，b，c": "根据双曲线方程求参数或a，b，c",
          "由a、b、c或定点求双曲线的标准方程": "由a、b、c或定点求双曲线的标准方程",
          "双曲线的轨迹问题": "双曲线的轨迹问题",
          "等轴双曲线": "等轴双曲线"
        },
        "双曲线的性质": {
          "求双曲线的焦点、焦距、顶点、实虚轴": "求双曲线的焦点、焦距、顶点、实虚轴",
          "求双曲线的离心率或离心率的取值范围": "求双曲线的离心率或离心率的取值范围",
          "根据离心率求双曲线的标准方程": "根据离心率求双曲线的标准方程",
          "已知方程求双曲线的渐近线": "已知方程求双曲线的渐近线",
          "已知双曲线的渐近线求方程": "已知双曲线的渐近线求方程"
        },
        "双曲线的应用": "双曲线的应用"
      },
      "抛物线": {
        "抛物线的定义": {
          "利用抛物线的定义解题": "利用抛物线的定义解题",
          "抛物线上的点到定点的距离及最值": "抛物线上的点到定点的距离及最值",
          "抛物线上的点到定点和焦点距离和、差最值": "抛物线上的点到定点和焦点距离和、差最值"
        },
        "抛物线的标准方程": {
          "根据抛物线方程求焦点、准线": "根据抛物线方程求焦点、准线",
          "抛物线的焦半径公式": "抛物线的焦半径公式",
          "求抛物线的标准方程": "求抛物线的标准方程",
          "抛物线的轨迹问题": "抛物线的轨迹问题",
          "抛物线的顶点、开口问题": "抛物线的顶点、开口问题"
        },
        "抛物线的应用": "抛物线的应用"
      },
      "直线与圆锥曲线的位置关系": {
        "直线与椭圆的位置关系": {
          "求直线与椭圆的交点": "求直线与椭圆的交点",
          "讨论椭圆与直线的位置关系": "讨论椭圆与直线的位置关系",
          "根据直线与椭圆的位置关系求参数或范围": "根据直线与椭圆的位置关系求参数或范围"
        },
        "椭圆的弦长、焦点弦": {
          "求椭圆中的弦长问题": "求椭圆中的弦长问题",
          "椭圆中三角形（多边形）的面积问题": "椭圆中三角形（多边形）的面积问题",
          "椭圆的中点弦": "椭圆的中点弦"
        },
        "椭圆中的参数范围及最值": {
          "求椭圆中的参数及范围": "求椭圆中的参数及范围",
          "求椭圆中的最值问题": "求椭圆中的最值问题"
        },
        "椭圆中的定点、定值问题": {
          "椭圆中的直线过定点问题": "椭圆中的直线过定点问题",
          "椭圆中定点的存在性问题": "椭圆中定点的存在性问题",
          "椭圆中的定值问题": "椭圆中的定值问题",
          "椭圆中的定直线问题": "椭圆中的定直线问题"
        },
        "直线与双曲线的位置关系": "直线与双曲线的位置关系",
        "双曲线的弦长、焦点弦问题": "双曲线的弦长、焦点弦问题",
        "双曲线中的参数范围及最值问题": "双曲线中的参数范围及最值问题",
        "双曲线中的定点、定值问题": "双曲线中的定点、定值问题",
        "直线与抛物线的位置关系": {
          "判断直线与抛物线的位置关系": "判断直线与抛物线的位置关系",
          "求直线与抛物线的交点": "求直线与抛物线的交点",
          "求抛物线的切线方程": "求抛物线的切线方程"
        },
        "抛物线的弦长、焦点弦": {
          "利用焦半径公式解抛物线问题": "利用焦半径公式解抛物线问题",
          "求抛物线的弦长问题": "求抛物线的弦长问题",
          "抛物线中三角形（多边形）的面积问题": "抛物线中三角形（多边形）的面积问题",
          "与抛物线焦点弦有关的几何性质": "与抛物线焦点弦有关的几何性质"
        },
        "抛物线中的参数范围及最值问题": "抛物线中的参数范围及最值问题",
        "抛物线中的定点、定值": {
          "抛物线中的定点问题": "抛物线中的定点问题",
          "抛物线中的定值问题": "抛物线中的定值问题",
          "抛物线中的定直线问题": "抛物线中的定直线问题"
        }
      },
      "圆锥曲线综合": {
        "圆锥曲线综合题": "圆锥曲线综合题",
        "圆锥曲线的实际应用": {
          "天体运动的轨道问题": "天体运动的轨道问题",
          "斜抛物体的轨迹问题": "斜抛物体的轨迹问题",
          "圆锥曲线的光学性质及其应用": "圆锥曲线的光学性质及其应用",
          "圆锥曲线在现代建筑中的体现": "圆锥曲线在现代建筑中的体现"
        }
      }
    }
  },
  "计数原理与概率统计": {
    "计数原理": {
      "加法原理与乘法原理": {
        "分类加法计数原理": "分类加法计数原理",
        "分步乘法计数原理": "分步乘法计数原理",
        "两个计数原理的综合应用": "两个计数原理的综合应用"
      },
      "排列": {
        "排列数的计算": "排列数的计算",
        "排列应用题": {
          "全排列问题": "全排列问题",
          "元素（位置）有限制的排列问题": "元素（位置）有限制的排列问题",
          "相邻以及不相邻问题": "相邻以及不相邻问题",
          "其他排列模型": "其他排列模型"
        }
      },
      "组合": {
        "组合数的计算": "组合数的计算",
        "实际问题中的组合计数问题": "实际问题中的组合计数问题",
        "分组分配问题": "分组分配问题"
      },
      "二项式定理": {
        "应用二项式定理解题": {
          "二项展开式的应用": "二项展开式的应用",
          "求二项展开式的第k项": "求二项展开式的第k项"
        },
        "二项式系数": {
          "求指定项的二项式系数": "求指定项的二项式系数",
          "二项式的系数和问题": "二项式的系数和问题"
        },
        "项的系数": {
          "求指定项的系数": "求指定项的系数",
          "求有理项或有理项的系数": "求有理项或有理项的系数",
          "由项的系数确定参数": "由项的系数确定参数",
          "二项展开式各项的系数和": "二项展开式各项的系数和",
          "求系数最大（小）的项": "求系数最大（小）的项",
          "奇次项与偶次项的系数和": "奇次项与偶次项的系数和"
        },
        "二项式定理的应用": {
          "多项式的展开式问题": "多项式的展开式问题",
          "利用二项式定理证明不等式": "利用二项式定理证明不等式",
          "利用二项式定理证明整除问题": "利用二项式定理证明整除问题",
          "利用二项式定理进行近似计算": "利用二项式定理进行近似计算"
        }
      },
      "排列组合综合问题": "排列组合综合问题"
    },
    "随机变量及其分布": {
      "全概率公式": "全概率公式",
      "贝叶斯公式": "贝叶斯公式",
      "离散型随机变量及其分布列": {
        "随机变量": "随机变量",
        "离散型随机变量": "离散型随机变量",
        "两点分布": "两点分布",
        "超几何分布": "超几何分布",
        "分布列的应用": {
          "求离散型随机变量的分布列": "求离散型随机变量的分布列",
          "求两点分布的分布列": "求两点分布的分布列",
          "求超几何分布的分布列": "求超几何分布的分布列",
          "利用分布列的性质求概率": "利用分布列的性质求概率",
          "随机变量函数的分布列": "随机变量函数的分布列"
        }
      },
      "二项分布及其应用": {
        "计算条件概率": "计算条件概率",
        "条件概率与独立事件": "条件概率与独立事件",
        "独立重复试验的概率问题": "独立重复试验的概率问题",
        "二项分布的应用": "二项分布的应用"
      },
      "离散型随机变量的均值及方差": {
        "求离散型随机变量的均值": "求离散型随机变量的均值",
        "离散型随机变量的方差": {
          "离散型随机变量的方差与标准差": "离散型随机变量的方差与标准差",
          "方差的作用及性质": "方差的作用及性质"
        },
        "常用分布的均值": {
          "超几何分布的均值": "超几何分布的均值",
          "两点分布的均值与方差": "两点分布的均值与方差",
          "二项分布的均值与方差": "二项分布的均值与方差"
        }
      },
      "正态分布": {
        "正态密度函数": "正态密度函数",
        "正态曲线的性质": "正态曲线的性质",
        "正态分布的概率问题": "正态分布的概率问题",
        "正态分布的实际应用": "正态分布的实际应用",
        "3σ原则": "3σ原则"
      }
    },
    "统计": {
      "随机抽样": {
        "普查和抽样": "普查和抽样",
        "总体与样本": "总体与样本",
        "简单随机抽样": {
          "简单的随机抽样的特征": "简单的随机抽样的特征",
          "抽签法": "抽签法",
          "随机数表法": "随机数表法"
        },
        "系统抽样": {
          "系统抽样的特征": "系统抽样的特征",
          "求系统抽样的组距与编号": "求系统抽样的组距与编号"
        },
        "分层抽样": {
          "分层抽样的特征": "分层抽样的特征",
          "分层抽样的相关计算": "分层抽样的相关计算"
        },
        "三种抽样方法的比较": "三种抽样方法的比较"
      },
      "用样本估计总体": {
        "统计图": {
          "条形统计图": "条形统计图",
          "折线统计图": "折线统计图",
          "扇形统计图": "扇形统计图",
          "频率分布表": "频率分布表"
        },
        "频率分布直方图": {
          "补全频率分布直方图": "补全频率分布直方图",
          "频率分布直方图的相关计算": "频率分布直方图的相关计算"
        },
        "频率分布折线图": "频率分布折线图",
        "茎叶图": "茎叶图",
        "百分位数": "百分位数",
        "众数、中位数、平均数": {
          "求众数、中位数、平均数": "求众数、中位数、平均数",
          "由频率分布直方图求中位数": "由频率分布直方图求中位数",
          "由频率分布直方图求平均数": "由频率分布直方图求平均数",
          "由茎叶图求中位数": "由茎叶图求中位数",
          "由茎叶图求平均数": "由茎叶图求平均数"
        },
        "极差、方差、标准差": {
          "计算数据的极差、方差、标准差": "计算数据的极差、方差、标准差",
          "用方差、标准差说明数据的波动程度": "用方差、标准差说明数据的波动程度"
        }
      }
    },
    "统计案例": {
      "变量间的相关关系": {
        "相关系数与向量夹角": "相关系数与向量夹角",
        "多组成对数据的相关性": "多组成对数据的相关性",
        "相关关系": "相关关系",
        "散点图": "散点图"
      },
      "线性回归模型": {
        "线性回归方程": {
          "回归直线方程的意义": "回归直线方程的意义",
          "用回归直线方程对总体进行估计": "用回归直线方程对总体进行估计",
          "根据回归直线方程求原数据中的值": "根据回归直线方程求原数据中的值",
          "最小二乘法求回归直线方程": "最小二乘法求回归直线方程"
        },
        "回归分析（残差分析）": "回归分析（残差分析）",
        "相关系数r的意义及辨析": "相关系数r的意义及辨析",
        "非线性回归": "非线性回归",
        "直线拟合": "直线拟合"
      },
      "独立性检验": {
        "完善列联表": "完善列联表",
        "等高条形图": "等高条形图",
        "卡方的计算": "卡方的计算",
        "独立性检验解决实际问题": "独立性检验解决实际问题",
        "2×2列联表独立性检验": "2×2列联表独立性检验",
        "样本相关系数计算": "样本相关系数计算"
      }
    },
    "概率": {
      "随机事件与概率": {
        "概率的基本性质": "概率的基本性质",
        "判断事件是否是随机事件": "判断事件是否是随机事件",
        "有限样本空间": "有限样本空间",
        "频率与概率": "频率与概率",
        "事件的关系和运算": {
          "确定所给事件的包含关系": "确定所给事件的包含关系",
          "事件的运算及其含义": "事件的运算及其含义",
          "互斥事件与对立事件关系的辨析": "互斥事件与对立事件关系的辨析",
          "求互斥事件的概率": "求互斥事件的概率",
          "求对立事件的概率": "求对立事件的概率"
        }
      },
      "事件的相互独立性": "事件的相互独立性",
      "古典概型": {
        "古典概型的特征": "古典概型的特征",
        "计算古典概型问题的概率": "计算古典概型问题的概率"
      },
      "几何概型": {
        "几何概型的特征": "几何概型的特征",
        "几何概型——长度型": "几何概型——长度型",
        "几何概型——面积型": "几何概型——面积型",
        "均匀随机数的产生": "均匀随机数的产生"
      },
      "概率综合题": "概率综合题"
    }
  },
  "推理与证明": {
    "合情推理与演绎推理": {
      "归纳推理": {
        "归纳推理概念辨析": "归纳推理概念辨析",
        "数与式的归纳推理": "数与式的归纳推理",
        "图与形的归纳推理": "图与形的归纳推理"
      },
      "类比推理": {
        "类比推理概念辨析": "类比推理概念辨析",
        "等差、等比数列中的类比推理": "等差、等比数列中的类比推理",
        "平面与空间中的类比": "平面与空间中的类比",
        "运算法则的类比": "运算法则的类比"
      },
      "演绎推理": {
        "演绎推理概念及辨析": "演绎推理概念及辨析",
        "大前提、小前提、结论的判断": "大前提、小前提、结论的判断",
        "三段论运用错误的分析": "三段论运用错误的分析"
      },
      "推理案例题": "推理案例题"
    },
    "直接证明与间接证明": {
      "综合法证明": "综合法证明",
      "分析法证明": "分析法证明",
      "反证法证明": "反证法证明"
    }
  },
  "算法与框图": {
    "算法初步": {
      "算法与程序框图": {
        "算法的概念": "算法的概念",
        "顺序结构框图": "顺序结构框图",
        "条件结构框图": "条件结构框图",
        "循环结构框图": "循环结构框图"
      },
      "基本算法语句": "基本算法语句",
      "算法案例": {
        "辗转相除法": "辗转相除法",
        "秦九韶算法": "秦九韶算法",
        "进位制": "进位制"
      }
    },
    "框图": {
      "流程图": "流程图",
      "结构图": "结构图"
    }
  },
  "复数": {
    "复数的概念": {
      "复数的基本概念": "复数的基本概念",
      "求复数的实部与虚部": "求复数的实部与虚部",
      "复数相等": "复数相等",
      "复数的模": {
        "求复数的模": "求复数的模",
        "由复数的模求参数": "由复数的模求参数",
        "与复数模相关的轨迹问题": "与复数模相关的轨迹问题"
      },
      "复数的分类": "复数的分类",
      "复数的几何意义": {
        "复数的坐标表示": "复数的坐标表示",
        "各象限内点对应的复数特征": "各象限内点对应的复数特征"
      }
    },
    "复数的四则运算": {
      "复数的加减": {
        "复数加减法的代数运算": "复数加减法的代数运算",
        "复数加减法几何意义的运用": "复数加减法几何意义的运用"
      },
      "复数的乘除和乘方": {
        "复数代数形式的乘法运算": "复数代数形式的乘法运算",
        "复数的乘方": "复数的乘方",
        "复数的除法运算": "复数的除法运算",
        "共轭复数": "共轭复数"
      },
      "复数的平方根与立方根": "复数的平方根与立方根",
      "复数的综合运算": "复数的综合运算"
    },
    "复数的三角表示": {
      "复数的三角表示式": {
        "复数的三角表示的相关概念": {
          "复数的辐角": "复数的辐角",
          "复数的三角形式": "复数的三角形式",
          "辐角的主值": "辐角的主值",
          "旋转任意角": "旋转任意角",
          "i^2=-1的几何意义": "i^2=-1的几何意义"
        },
        "复数的代数形式转化为三角形式": "复数的代数形式转化为三角形式",
        "复数的三角形式转化为代数形式": "复数的三角形式转化为代数形式"
      },
      "复数乘、除运算的三角表示及其几何意义": {
        "复数乘法运算的三角表示及与代数形式的相互转化": "复数乘法运算的三角表示及与代数形式的相互转化",
        "复数乘法运算的三角表示的几何意义": "复数乘法运算的三角表示的几何意义",
        "复数除法运算的三角表示及与代数形式的相互转化": "复数除法运算的三角表示及与代数形式的相互转化",
        "复数除法运算的三角表示的几何意义": "复数除法运算的三角表示的几何意义",
        "复数的乘除混合运算的三角表示": "复数的乘除混合运算的三角表示",
        "复数乘、除运算的三角表示的应用": "复数乘、除运算的三角表示的应用"
      }
    }
  },
  "坐标系与参数方程": {
    "平面直角坐标系": {
      "坐标系中的相关计算": "坐标系中的相关计算",
      "平面直角坐标系中的变换": "平面直角坐标系中的变换"
    },
    "极坐标系": {
      "用极坐标表示点的位置": "用极坐标表示点的位置",
      "极坐标与直角坐标的互化": "极坐标与直角坐标的互化",
      "极坐标下两点距离的计算": "极坐标下两点距离的计算"
    },
    "简单曲线的极坐标方程": {
      "曲线的极坐标方程定义及其意义": "曲线的极坐标方程定义及其意义",
      "圆的极坐标方程": "圆的极坐标方程",
      "直线的极坐标方程": "直线的极坐标方程",
      "普通方程与极坐标方程的互化": "普通方程与极坐标方程的互化",
      "圆锥曲线的极坐标方程": "圆锥曲线的极坐标方程",
      "柱坐标系与球坐标系": "柱坐标系与球坐标系"
    },
    "曲线的参数方程": {
      "参数方程": {
        "参数方程的概念": "参数方程的概念",
        "圆的参数方程": "圆的参数方程",
        "圆锥曲线的参数方程": "圆锥曲线的参数方程"
      },
      "参数方程与普通方程的互化": {
        "参数方程化为普通方程": "参数方程化为普通方程",
        "普通方程化为参数方程": "普通方程化为参数方程"
      }
    },
    "直线的参数方程": {
      "直线的参数方程": "直线的参数方程",
      "利用弦长公式求弦长": "利用弦长公式求弦长",
      "利用直线的参数方程研究直线与曲线的位置关系": "利用直线的参数方程研究直线与曲线的位置关系",
      "渐开线与摆线": "渐开线与摆线",
      "数形结合法解参数方程有关问题": "数形结合法解参数方程有关问题",
      "坐标系与参数方程中的范围与定值问题": "坐标系与参数方程中的范围与定值问题"
    }
  },
  "不等式选讲": {
    "三元基本（均值）不等式": "三元基本（均值）不等式",
    "绝对值不等式": {
      "含绝对值不等式的证明": {
        "分类讨论证明绝对值不等式": "分类讨论证明绝对值不等式",
        "几何意义证明绝对值不等式": "几何意义证明绝对值不等式",
        "绝对值三角不等式的应用": "绝对值三角不等式的应用"
      },
      "含绝对值不等式的解法": {
        "分类讨论解绝对值不等式": "分类讨论解绝对值不等式",
        "几何意义解绝对值不等式": "几何意义解绝对值不等式",
        "图象法解绝对值不等式": "图象法解绝对值不等式",
        "解含参数的绝对值不等式": "解含参数的绝对值不等式",
        "求绝对值不等式中参数值或范围": "求绝对值不等式中参数值或范围"
      }
    },
    "柯西不等式": {
      "利用柯西不等式求最值": "利用柯西不等式求最值",
      "利用柯西不等式求参数的范围": "利用柯西不等式求参数的范围",
      "利用柯西不等式进行证明": "利用柯西不等式进行证明",
      "柯西不等式的其他应用": "柯西不等式的其他应用"
    },
    "排序不等式": "排序不等式",
    "证明不等式的基本方法": {
      "比较法证明不等式": {
        "作差比较法证明不等式": "作差比较法证明不等式",
        "作商比较法证明不等式": "作商比较法证明不等式"
      },
      "综合法证明不等式": "综合法证明不等式",
      "分析法证明不等式": "分析法证明不等式",
      "反证法证明不等式": "反证法证明不等式",
      "放缩法证明不等式": "放缩法证明不等式",
      "数学归纳法证明不等式问题": "数学归纳法证明不等式问题"
    }
  },
  "矩阵与变换": {
    "线性变换与二阶矩阵": "线性变换与二阶矩阵",
    "矩阵乘法": "矩阵乘法",
    "逆变换与逆矩阵": "逆变换与逆矩阵",
    "矩阵的特征向量": "矩阵的特征向量"
  },
  "新定义": {
    "集合": "集合",
    "三角函数": "三角函数",
    "平面向量": "平面向量",
    "解三角形": "解三角形",
    "复数": "复数",
    "立体几何": "立体几何",
    "数列": "数列",
    "空间向量": "空间向量",
    "解析几何": "解析几何",
    "概率统计": "概率统计"
  }
}